{
  "version": "1.0",
  "engine": "darwin|Transformer|1.35.0|latest|latest",
  "containerized": false,
  "host_distro": {
    "name": "",
    "version": "",
    "display_name": "Big Sur (11.3)"
  },
  "type": "build",
  "state": "done",
  "target_reference": "megabytelabs/updater:latest",
  "system": {
    "type": "Linux",
    "release": "5.10.25-linuxkit",
    "distro": {
      "name": "Alpine Linux",
      "version": "3.14.0",
      "display_name": "Alpine Linux v3.14"
    }
  },
  "source_image": {
    "identity": {
      "id": "sha256:77606dd0dfb130107a930aab251c4cf176ac07c6763cc1a75cf9c14d1bc5c37e",
      "tags": ["0.0.47", "latest"],
      "names": ["megabytelabs/updater:0.0.47", "megabytelabs/updater:latest"]
    },
    "size": 274920320,
    "size_human": "275 MB",
    "create_time": "2021-06-22T23:54:39Z",
    "docker_version": "",
    "architecture": "amd64",
    "os": "linux",
    "labels": {
      "maintainer": "Megabyte Labs <help@megabyte.space",
      "org.opencontainers.image.authors": "Brian Zalewski <brian@megabyte.space>",
      "org.opencontainers.image.created": "2021-06-22T19:49:13-04:00",
      "org.opencontainers.image.description": "Node.js files/configurations that support the creation of Dockerfiles",
      "org.opencontainers.image.documentation": "https://gitlab.com/megabyte-labs/dockerfile/ci-pipeline/updater/-/blob/master/README.md",
      "org.opencontainers.image.licenses": "MIT",
      "org.opencontainers.image.revision": "f8fc15400b10af192b849fe1c360d4a27b7f1a19",
      "org.opencontainers.image.source": "https://gitlab.com/megabyte-labs/dockerfile/ci-pipeline/updater.git",
      "org.opencontainers.image.url": "https://megabyte.space",
      "org.opencontainers.image.vendor": "Megabyte Labs",
      "org.opencontainers.image.version": "0.0.47",
      "space.megabyte.type": "ci-pipeline"
    },
    "env_vars": [
      "PATH=/usr/local/sbin:/usr/local/bin:/usr/sbin:/usr/bin:/sbin:/bin",
      "container=docker",
      "NODE_EXTRA_CA_CERTS=/etc/ssl/certs/ca-certificates.crt",
      "TASK_RELEASE_URL=https://github.com/go-task/task/releases/latest",
      "YQ_RELEASE_URL=https://github.com/mikefarah/yq/releases/latest/download/yq_linux_amd64"
    ]
  },
  "minified_image_size": 107573195,
  "minified_image_size_human": "108 MB",
  "minified_image": "megabytelabs/updater:slim",
  "minified_image_has_data": true,
  "minified_by": 2.555658219503474,
  "artifact_location": "/tmp/docker-slim-state/.docker-slim-state/images/77606dd0dfb130107a930aab251c4cf176ac07c6763cc1a75cf9c14d1bc5c37e/artifacts",
  "container_report_name": "creport.json",
  "seccomp_profile_name": "megabytelabs-updater-seccomp.json",
  "apparmor_profile_name": "megabytelabs-updater-apparmor-profile",
  "image_stack": [
    {
      "is_top_image": true,
      "id": "sha256:77606dd0dfb130107a930aab251c4cf176ac07c6763cc1a75cf9c14d1bc5c37e",
      "full_name": "megabytelabs/updater:0.0.47",
      "repo_name": "megabytelabs/updater",
      "version_tag": "0.0.47",
      "raw_tags": ["megabytelabs/updater:0.0.47", "megabytelabs/updater:latest"],
      "create_time": "2021-06-22T23:54:39Z",
      "new_size": 274920320,
      "new_size_human": "275 MB",
      "instructions": [
        {
          "type": "ADD",
          "time": "2021-06-15T22:19:37Z",
          "is_nop": true,
          "local_image_exists": false,
          "layer_index": 0,
          "size": 5595013,
          "size_human": "5.6 MB",
          "params": "file:f278386b0cef68136129f5f58c52445590a417b624d62bca158d4dc926c340df in /",
          "command_snippet": "ADD file:f278386b0cef68136129f5f58c52445590a...",
          "command_all": "ADD file:f278386b0cef68136129f5f58c52445590a417b624d62bca158d4dc926c340df /",
          "target": "/",
          "source_type": "file"
        },
        {
          "type": "CMD",
          "time": "2021-06-15T22:19:37Z",
          "is_nop": true,
          "is_exec_form": true,
          "local_image_exists": false,
          "layer_index": 0,
          "size": 0,
          "params": "[\"/bin/sh\"]",
          "command_snippet": "CMD [\"/bin/sh\"]",
          "command_all": "CMD [\"/bin/sh\"]"
        },
        {
          "type": "RUN",
          "time": "2021-06-22T23:54:39Z",
          "is_nop": false,
          "is_exec_form": true,
          "local_image_exists": false,
          "layer_index": 0,
          "size": 0,
          "command_snippet": "RUN [\"ENV\",\"container=docker\"]",
          "command_all": "RUN [\"ENV\",\"container=docker\"]",
          "system_commands": ["[\"ENV\",\"container=docker\"]"],
          "comment": "buildkit.dockerfile.v0"
        },
        {
          "type": "RUN",
          "time": "2021-06-22T23:54:39Z",
          "is_nop": false,
          "is_exec_form": true,
          "local_image_exists": false,
          "layer_index": 0,
          "size": 0,
          "command_snippet": "RUN [\"ENV\",\"NODE_EXTRA_CA_CERTS=/etc/ssl/cer...",
          "command_all": "RUN [\"ENV\",\"NODE_EXTRA_CA_CERTS=/etc/ssl/certs/ca-certificates.crt\"]",
          "system_commands": ["[\"ENV\",\"NODE_EXTRA_CA_CERTS=/etc/ssl/certs/ca-certificates.crt\"]"],
          "comment": "buildkit.dockerfile.v0"
        },
        {
          "type": "RUN",
          "time": "2021-06-22T23:54:39Z",
          "is_nop": false,
          "is_exec_form": true,
          "local_image_exists": false,
          "layer_index": 0,
          "size": 0,
          "command_snippet": "RUN [\"ENV\",\"TASK_RELEASE_URL=https://github....",
          "command_all": "RUN [\"ENV\",\"TASK_RELEASE_URL=https://github.com/go-task/task/releases/latest\"]",
          "system_commands": ["[\"ENV\",\"TASK_RELEASE_URL=https://github.com/go-task/task/releases/latest\"]"],
          "comment": "buildkit.dockerfile.v0"
        },
        {
          "type": "RUN",
          "time": "2021-06-22T23:54:39Z",
          "is_nop": false,
          "is_exec_form": true,
          "local_image_exists": false,
          "layer_index": 0,
          "size": 0,
          "command_snippet": "RUN [\"ENV\",\"YQ_RELEASE_URL=https://github.co...",
          "command_all": "RUN [\"ENV\",\"YQ_RELEASE_URL=https://github.com/mikefarah/yq/releases/latest/download/yq_linux_amd64\"]",
          "system_commands": [
            "[\"ENV\",\"YQ_RELEASE_URL=https://github.com/mikefarah/yq/releases/latest/download/yq_linux_amd64\"]"
          ],
          "comment": "buildkit.dockerfile.v0"
        },
        {
          "type": "RUN",
          "time": "2021-06-22T23:54:39Z",
          "is_nop": false,
          "is_exec_form": true,
          "local_image_exists": false,
          "layer_index": 0,
          "size": 269325307,
          "size_human": "269 MB",
          "command_snippet": "RUN [\"RUN\",\"/bin/sh\",\"-c\",\"apk\",\"--no-cache\"...",
          "command_all": "RUN [\"RUN\",\"/bin/sh\",\"-c\",\"apk\",\"--no-cache\",\"add\",\"--virtual\",\"build-dependencies\",\"perl~=5\",\"upx~=3\",\"\\u0026\\u0026\",\"apk\",\"--no-cache\",\"add\",\"bash~=5\",\"curl~=7\",\"git~=2\",\"jq~=1\",\"nodejs~=14\",\"npm~=7\",\"python3~=3\",\"py3-pip~=20\",\"py3-wheel~=0\",\"\\u0026\\u0026\",\"curl\",\"-OL\",\"$TASK_RELEASE_URL/download/task_linux_amd64.tar.gz\",\"\\u0026\\u0026\",\"tar\",\"-xzvf\",\"task_linux_amd64.tar.gz\",\"\\u0026\\u0026\",\"mv\",\"task\",\"/usr/local/bin/task\",\"\\u0026\\u0026\",\"chmod\",\"+x\",\"/usr/local/bin/task\",\"\\u0026\\u0026\",\"upx\",\"/usr/local/bin/task\",\"\\u0026\\u0026\",\"curl\",\"$YQ_RELEASE_URL/download/yq_linux_amd64\",\"-o\",\"/usr/local/bin/yq\",\"\\u0026\\u0026\",\"chmod\",\"+x\",\"/usr/local/bin/yq\",\"\\u0026\\u0026\",\"npm\",\"install\",\"-g\",\"@appnest/readme\",\"@megabytelabs/prettier-config@latest\",\"@megabytelabs/prettier-config-ansible@latest\",\"hbs-cli@latest\",\"npm@latest\",\"prettier@latest\",\"prettier-plugin-sh@latest\",\"prettier-package-json@latest\",\"\\u0026\\u0026\",\"pip3\",\"install\",\"--no-cache-dir\",\"virtualenv==20.*\",\"\\u0026\\u0026\",\"apk\",\"del\",\"build-dependencies\"]",
          "system_commands": [
            "[\"RUN\",\"/bin/sh\",\"-c\",\"apk\",\"--no-cache\",\"add\",\"--virtual\",\"build-dependencies\",\"perl~=5\",\"upx~=3\",\"u0026u0026\",\"apk\",\"--no-cache\",\"add\",\"bash~=5\",\"curl~=7\",\"git~=2\",\"jq~=1\",\"nodejs~=14\",\"npm~=7\",\"python3~=3\",\"py3-pip~=20\",\"py3-wheel~=0\",\"u0026u0026\",\"curl\",\"-OL\",\"$TASK_RELEASE_URL/download/task_linux_amd64.tar.gz\",\"u0026u0026\",\"tar\",\"-xzvf\",\"task_linux_amd64.tar.gz\",\"u0026u0026\",\"mv\",\"task\",\"/usr/local/bin/task\",\"u0026u0026\",\"chmod\",\"+x\",\"/usr/local/bin/task\",\"u0026u0026\",\"upx\",\"/usr/local/bin/task\",\"u0026u0026\",\"curl\",\"$YQ_RELEASE_URL/download/yq_linux_amd64\",\"-o\",\"/usr/local/bin/yq\",\"u0026u0026\",\"chmod\",\"+x\",\"/usr/local/bin/yq\",\"u0026u0026\",\"npm\",\"install\",\"-g\",\"@appnest/readme\",\"@megabytelabs/prettier-config@latest\",\"@megabytelabs/prettier-config-ansible@latest\",\"hbs-cli@latest\",\"npm@latest\",\"prettier@latest\",\"prettier-plugin-sh@latest\",\"prettier-package-json@latest\",\"u0026u0026\",\"pip3\",\"install\",\"--no-cache-dir\",\"virtualenv==20.*\",\"u0026u0026\",\"apk\",\"del\",\"build-dependencies\"]"
          ],
          "comment": "buildkit.dockerfile.v0"
        },
        {
          "type": "RUN",
          "time": "2021-06-22T23:54:39Z",
          "is_nop": false,
          "is_exec_form": true,
          "local_image_exists": false,
          "layer_index": 0,
          "size": 0,
          "command_snippet": "RUN [\"WORKDIR\",\"/work\"]",
          "command_all": "RUN [\"WORKDIR\",\"/work\"]",
          "system_commands": ["[\"WORKDIR\",\"/work\"]"],
          "comment": "buildkit.dockerfile.v0"
        },
        {
          "type": "RUN",
          "time": "2021-06-22T23:54:39Z",
          "is_nop": false,
          "is_exec_form": true,
          "local_image_exists": false,
          "layer_index": 0,
          "size": 0,
          "command_snippet": "RUN [\"ARG\",\"BUILD_DATE\"]",
          "command_all": "RUN [\"ARG\",\"BUILD_DATE\"]",
          "system_commands": ["[\"ARG\",\"BUILD_DATE\"]"],
          "comment": "buildkit.dockerfile.v0"
        },
        {
          "type": "RUN",
          "time": "2021-06-22T23:54:39Z",
          "is_nop": false,
          "is_exec_form": true,
          "local_image_exists": false,
          "layer_index": 0,
          "size": 0,
          "command_snippet": "RUN [\"ARG\",\"REVISION\"]",
          "command_all": "RUN [\"ARG\",\"REVISION\"]",
          "system_commands": ["[\"ARG\",\"REVISION\"]"],
          "comment": "buildkit.dockerfile.v0"
        },
        {
          "type": "RUN",
          "time": "2021-06-22T23:54:39Z",
          "is_nop": false,
          "is_exec_form": true,
          "local_image_exists": false,
          "layer_index": 0,
          "size": 0,
          "command_snippet": "RUN [\"ARG\",\"VERSION\"]",
          "command_all": "RUN [\"ARG\",\"VERSION\"]",
          "system_commands": ["[\"ARG\",\"VERSION\"]"],
          "comment": "buildkit.dockerfile.v0"
        },
        {
          "type": "RUN",
          "time": "2021-06-22T23:54:39Z",
          "is_nop": false,
          "is_exec_form": true,
          "local_image_exists": false,
          "layer_index": 0,
          "size": 0,
          "command_snippet": "RUN [\"LABEL\",\"maintainer=Megabyte\",\"Labs\",\"\\...",
          "command_all": "RUN [\"LABEL\",\"maintainer=Megabyte\",\"Labs\",\"\\u003chelp@megabyte.space\"]",
          "system_commands": ["[\"LABEL\",\"maintainer=Megabyte\",\"Labs\",\"u003chelp@megabyte.space\"]"],
          "comment": "buildkit.dockerfile.v0"
        },
        {
          "type": "RUN",
          "time": "2021-06-22T23:54:39Z",
          "is_nop": false,
          "is_exec_form": true,
          "local_image_exists": false,
          "layer_index": 0,
          "size": 0,
          "command_snippet": "RUN [\"LABEL\",\"org.opencontainers.image.autho...",
          "command_all": "RUN [\"LABEL\",\"org.opencontainers.image.authors=Brian\",\"Zalewski\",\"\\u003cbrian@megabyte.space\\u003e\"]",
          "system_commands": [
            "[\"LABEL\",\"org.opencontainers.image.authors=Brian\",\"Zalewski\",\"u003cbrian@megabyte.spaceu003e\"]"
          ],
          "comment": "buildkit.dockerfile.v0"
        },
        {
          "type": "RUN",
          "time": "2021-06-22T23:54:39Z",
          "is_nop": false,
          "is_exec_form": true,
          "local_image_exists": false,
          "layer_index": 0,
          "size": 0,
          "command_snippet": "RUN [\"LABEL\",\"org.opencontainers.image.creat...",
          "command_all": "RUN [\"LABEL\",\"org.opencontainers.image.created=2021-06-22T19:49:13-04:00\"]",
          "system_commands": ["[\"LABEL\",\"org.opencontainers.image.created=2021-06-22T19:49:13-04:00\"]"],
          "comment": "buildkit.dockerfile.v0"
        },
        {
          "type": "RUN",
          "time": "2021-06-22T23:54:39Z",
          "is_nop": false,
          "is_exec_form": true,
          "local_image_exists": false,
          "layer_index": 0,
          "size": 0,
          "command_snippet": "RUN [\"LABEL\",\"org.opencontainers.image.descr...",
          "command_all": "RUN [\"LABEL\",\"org.opencontainers.image.description=Node.js\",\"files/configurations\",\"that\",\"support\",\"the\",\"creation\",\"of\",\"Dockerfiles\"]",
          "system_commands": [
            "[\"LABEL\",\"org.opencontainers.image.description=Node.js\",\"files/configurations\",\"that\",\"support\",\"the\",\"creation\",\"of\",\"Dockerfiles\"]"
          ],
          "comment": "buildkit.dockerfile.v0"
        },
        {
          "type": "RUN",
          "time": "2021-06-22T23:54:39Z",
          "is_nop": false,
          "is_exec_form": true,
          "local_image_exists": false,
          "layer_index": 0,
          "size": 0,
          "command_snippet": "RUN [\"LABEL\",\"org.opencontainers.image.docum...",
          "command_all": "RUN [\"LABEL\",\"org.opencontainers.image.documentation=https://gitlab.com/megabyte-labs/dockerfile/ci-pipeline/updater/-/blob/master/README.md\"]",
          "system_commands": [
            "[\"LABEL\",\"org.opencontainers.image.documentation=https://gitlab.com/megabyte-labs/dockerfile/ci-pipeline/updater/-/blob/master/README.md\"]"
          ],
          "comment": "buildkit.dockerfile.v0"
        },
        {
          "type": "RUN",
          "time": "2021-06-22T23:54:39Z",
          "is_nop": false,
          "is_exec_form": true,
          "local_image_exists": false,
          "layer_index": 0,
          "size": 0,
          "command_snippet": "RUN [\"LABEL\",\"org.opencontainers.image.licen...",
          "command_all": "RUN [\"LABEL\",\"org.opencontainers.image.licenses=MIT\"]",
          "system_commands": ["[\"LABEL\",\"org.opencontainers.image.licenses=MIT\"]"],
          "comment": "buildkit.dockerfile.v0"
        },
        {
          "type": "RUN",
          "time": "2021-06-22T23:54:39Z",
          "is_nop": false,
          "is_exec_form": true,
          "local_image_exists": false,
          "layer_index": 0,
          "size": 0,
          "command_snippet": "RUN [\"LABEL\",\"org.opencontainers.image.revis...",
          "command_all": "RUN [\"LABEL\",\"org.opencontainers.image.revision=f8fc15400b10af192b849fe1c360d4a27b7f1a19\"]",
          "system_commands": [
            "[\"LABEL\",\"org.opencontainers.image.revision=f8fc15400b10af192b849fe1c360d4a27b7f1a19\"]"
          ],
          "comment": "buildkit.dockerfile.v0"
        },
        {
          "type": "RUN",
          "time": "2021-06-22T23:54:39Z",
          "is_nop": false,
          "is_exec_form": true,
          "local_image_exists": false,
          "layer_index": 0,
          "size": 0,
          "command_snippet": "RUN [\"LABEL\",\"org.opencontainers.image.sourc...",
          "command_all": "RUN [\"LABEL\",\"org.opencontainers.image.source=https://gitlab.com/megabyte-labs/dockerfile/ci-pipeline/updater.git\"]",
          "system_commands": [
            "[\"LABEL\",\"org.opencontainers.image.source=https://gitlab.com/megabyte-labs/dockerfile/ci-pipeline/updater.git\"]"
          ],
          "comment": "buildkit.dockerfile.v0"
        },
        {
          "type": "RUN",
          "time": "2021-06-22T23:54:39Z",
          "is_nop": false,
          "is_exec_form": true,
          "local_image_exists": false,
          "layer_index": 0,
          "size": 0,
          "command_snippet": "RUN [\"LABEL\",\"org.opencontainers.image.url=h...",
          "command_all": "RUN [\"LABEL\",\"org.opencontainers.image.url=https://megabyte.space\"]",
          "system_commands": ["[\"LABEL\",\"org.opencontainers.image.url=https://megabyte.space\"]"],
          "comment": "buildkit.dockerfile.v0"
        },
        {
          "type": "RUN",
          "time": "2021-06-22T23:54:39Z",
          "is_nop": false,
          "is_exec_form": true,
          "local_image_exists": false,
          "layer_index": 0,
          "size": 0,
          "command_snippet": "RUN [\"LABEL\",\"org.opencontainers.image.vendo...",
          "command_all": "RUN [\"LABEL\",\"org.opencontainers.image.vendor=Megabyte\",\"Labs\"]",
          "system_commands": ["[\"LABEL\",\"org.opencontainers.image.vendor=Megabyte\",\"Labs\"]"],
          "comment": "buildkit.dockerfile.v0"
        },
        {
          "type": "RUN",
          "time": "2021-06-22T23:54:39Z",
          "is_nop": false,
          "is_exec_form": true,
          "local_image_exists": false,
          "layer_index": 0,
          "size": 0,
          "command_snippet": "RUN [\"LABEL\",\"org.opencontainers.image.versi...",
          "command_all": "RUN [\"LABEL\",\"org.opencontainers.image.version=0.0.47\"]",
          "system_commands": ["[\"LABEL\",\"org.opencontainers.image.version=0.0.47\"]"],
          "comment": "buildkit.dockerfile.v0"
        },
        {
          "type": "RUN",
          "time": "2021-06-22T23:54:39Z",
          "is_last_instruction": true,
          "is_nop": false,
          "is_exec_form": true,
          "local_image_exists": true,
          "layer_index": 0,
          "size": 0,
          "command_snippet": "RUN [\"LABEL\",\"space.megabyte.type=ci-pipelin...",
          "command_all": "RUN [\"LABEL\",\"space.megabyte.type=ci-pipeline\"]",
          "system_commands": ["[\"LABEL\",\"space.megabyte.type=ci-pipeline\"]"],
          "comment": "buildkit.dockerfile.v0",
          "raw_tags": ["megabytelabs/updater:0.0.47", "megabytelabs/updater:latest"]
        }
      ]
    }
  ]
}
